fullstack/__init__.py
fullstack/components.py
fullstack/config.py
fullstack/dispatcher.py
fullstack/dom.py
fullstack/server.py
fullstack/utils.py
fullstack/async_utils/__init__.py
fullstack/async_utils/debouncer.py
fullstack/async_utils/later.py
fullstack/events/__init__.py
fullstack/events/clipboard.py
fullstack/events/event_mixins.py
fullstack/events/hash_change.py
fullstack/events/ui/__init__.py
fullstack/events/ui/focus.py
fullstack/events/ui/input.py
fullstack/events/ui/keyboard.py
fullstack/events/ui/ui.py
fullstack/events/ui/mouse/__init__.py
fullstack/events/ui/mouse/drag.py
fullstack/events/ui/mouse/mouse.py
fullstack/events/ui/mouse/wheel.py
fullstack-0.0.2.dist-info/AUTHORS.rst
fullstack-0.0.2.dist-info/LICENSE
fullstack-0.0.2.dist-info/METADATA
fullstack-0.0.2.dist-info/WHEEL
fullstack-0.0.2.dist-info/top_level.txt
fullstack-0.0.2.dist-info/RECORD
